X2015HulianwangQiyeXiaozhaoBishiTi/README.md
X2015HulianwangQiyeXiaozhaoBishiTi/__init__.py
X2015HulianwangQiyeXiaozhaoBishiTi/__main__.py
X2015HulianwangQiyeXiaozhaoBishiTi/file.pdf
X2015HulianwangQiyeXiaozhaoBishiTi/index.html
x2015_hulianwang_qiye_xiaozhao_bishi_ti-2024.2.29.0.dist-info/METADATA
x2015_hulianwang_qiye_xiaozhao_bishi_ti-2024.2.29.0.dist-info/WHEEL
x2015_hulianwang_qiye_xiaozhao_bishi_ti-2024.2.29.0.dist-info/entry_points.txt
x2015_hulianwang_qiye_xiaozhao_bishi_ti-2024.2.29.0.dist-info/top_level.txt
x2015_hulianwang_qiye_xiaozhao_bishi_ti-2024.2.29.0.dist-info/RECORD
